main.py
responder/__init__.py
responder/responder.py
firebase_responder-1.0.6.dist-info/METADATA
firebase_responder-1.0.6.dist-info/WHEEL
firebase_responder-1.0.6.dist-info/licenses/license
firebase_responder-1.0.6.dist-info/RECORD
