Metadata-Version: 2.1
Name: firebase-responder
Version: 1.0.6
Summary: Used to perform predetermined function calls on IoT devices when a given value in Firebase RTDB is detected. Actions are performed asynchronously and delays/args can be used to customize responses.
Author: edward62740
License: MIT License
Classifier: License :: OSI Approved :: MIT License
Classifier: Operating System :: OS Independent
Classifier: Programming Language :: Python :: 3
Requires-Python: >=3.7
